programs/__init__.py
programs/ant_colony_algorithm.py
programs/binary_optimization.py
programs/continuous_optimization.py
programs/gray_wolf_optimization.py
programs/particle_swarn_optimization.py
programs/shuffuled_frog_optimization.py
programs/simulated_annealing.py
programs/tabu_search.py
programs/tsp.py
dharun-1.3.dist-info/METADATA
dharun-1.3.dist-info/WHEEL
dharun-1.3.dist-info/top_level.txt
dharun-1.3.dist-info/RECORD
