Metadata-Version: 2.1
Name: dharun
Version: 1.3
Summary: Some Optimization Problems for Machine Learning
Home-page: https://github.com/KeerthiVasan-ai/optimization-techniques
Author: Dharun
Author-email: leodas@gmail.com
Classifier: Programming Language :: Python :: 3
Classifier: License :: OSI Approved :: MIT License
Classifier: Operating System :: OS Independent
